data_structures/ResourceInfo.py
data_structures/RosterInfo.py
data_structures/RosterManager.py
data_structures/concurrency_info.py
data_structures/event_log_info.py
data_structures/nsga2_problem.py
data_structures/pools_info.py
data_structures/priority_queue.py
data_structures/simulation_info.py
data_structures/solution_space.py
pareto_algorithms_and_metrics/alg_hill_climb_tabu_search.py
pareto_algorithms_and_metrics/hill_climb.py
pareto_algorithms_and_metrics/iterations_handler.py
pareto_algorithms_and_metrics/main.py
pareto_algorithms_and_metrics/pareto_metrics.py
support_modules/bpmn_parser.py
support_modules/constraints_generator.py
support_modules/file_manager.py
support_modules/helpers.py
support_modules/json_manager.py
support_modules/key_generator.py
support_modules/log_parser.py
support_modules/plot_statistics_handler.py
support_modules/prosimos_simulation_runner.py
support_modules/simulation_runner.py
optimos-0.9.6.dist-info/METADATA
optimos-0.9.6.dist-info/WHEEL
optimos-0.9.6.dist-info/RECORD
