Metadata-Version: 2.1
Name: optimos
Version: 0.9.6
Summary: Optimos is a resource allocation optimization engine for business processes with differentiated resources. Part of PIX toolset
Author: Jonas Berx
Author-email: jonas.berx@ut.ee
Requires-Python: >=3.9,<3.12
Classifier: Programming Language :: Python :: 3
Classifier: Programming Language :: Python :: 3.9
Classifier: Programming Language :: Python :: 3.10
Classifier: Programming Language :: Python :: 3.11
Requires-Dist: click (>=8.1.3,<9.0.0)
Requires-Dist: numpy (>=1.24.3,<2.0.0)
Requires-Dist: pandas (>=2.0.1,<3.0.0)
Requires-Dist: pix-framework (>=0.8.7,<0.9.0)
Requires-Dist: pm4py (>=2.7.4,<3.0.0)
Requires-Dist: prosimos (>=1.2.4,<2.0.0)
Requires-Dist: python-dateutil (>=2.8.2,<3.0.0)
Requires-Dist: pytz (>=2023.3,<2024.0)
Requires-Dist: scipy (>=1.10.1,<2.0.0)
Requires-Dist: simpy (>=4.0.1,<5.0.0)
